data/ntsz_grid_broken.fits
data/ntsz_grid_single.fits
data/planck_bandpass.fits
docs/conf.py
ntsz/__init__.py
ntsz/ntsz.py
ntsz/ntsz_grid_generator.py
ntsz/ntsz_utils.py
ntsz/planck_bandpass.py
ntsz-1.2.dist-info/licenses/LICENSE
tests/__init__.py
tests/test_tsz.py
ntsz-1.2.dist-info/METADATA
ntsz-1.2.dist-info/WHEEL
ntsz-1.2.dist-info/top_level.txt
ntsz-1.2.dist-info/RECORD
