Metadata-Version: 2.4
Name: ntsz
Version: 1.2
Summary: A python 3 implementation for calculation of various Sunyaev        -Zeldovich effects.
Home-page: https://github.com/Vyoma-M/ntsz
Author: Vyoma Muralidhara
Author-email: vyoma1993@gmail.com
Classifier: Programming Language :: Python :: 3
Classifier: Intended Audience :: Developers
Classifier: Intended Audience :: Science/Research
Classifier: License :: OSI Approved :: MIT License
Classifier: Operating System :: OS Independent
Requires-Python: >=3.6
License-File: LICENSE
Requires-Dist: healpy
Requires-Dist: numpy
Requires-Dist: scipy
Requires-Dist: astropy
Dynamic: author
Dynamic: author-email
Dynamic: classifier
Dynamic: description
Dynamic: description-content-type
Dynamic: home-page
Dynamic: license-file
Dynamic: requires-dist
Dynamic: requires-python
Dynamic: summary
